lightsaillogger/__init__.py
lightsaillogger/logger.py
lightsaillogger-0.1.5.dist-info/LICENSE
lightsaillogger-0.1.5.dist-info/METADATA
lightsaillogger-0.1.5.dist-info/WHEEL
lightsaillogger-0.1.5.dist-info/top_level.txt
lightsaillogger-0.1.5.dist-info/RECORD
