Metadata-Version: 2.1
Name: lightsaillogger
Version: 0.1.5
Summary: Log all your lightsail containers in 1 log file
Home-page: https://github.com/two-trick-pony-NL/LightSailLogger
Author: Peter van Doorn
Author-email: peter@petervandoorn.com
Classifier: Programming Language :: Python :: 3
Classifier: License :: OSI Approved :: MIT License
Classifier: Operating System :: OS Independent
Requires-Python: >=3.8
License-File: LICENSE
